MANIFEST.in
README.rst
setup.py
sphinx_links/__init__.py
sphinx_links/collection.py
sphinx_links.egg-info/PKG-INFO
sphinx_links.egg-info/SOURCES.txt
sphinx_links.egg-info/dependency_links.txt
sphinx_links.egg-info/not-zip-safe
sphinx_links.egg-info/top_level.txt