Metadata-Version: 1.1
Name: sphinx-links
Version: 0.0.2
Summary: Added external links to Sphinx project as :l:`name of link`.
Home-page: https://github.com/ITCase/sphinx-links
Author: uralbash
Author-email: sacrud@uralbash.ru
License: UNKNOWN
Keywords: sphinx documentation
Platform: UNKNOWN
Classifier: Environment :: Web Environment
Classifier: Intended Audience :: Developers
Classifier: Intended Audience :: System Administrators
Classifier: Programming Language :: Python
Classifier: License :: Repoze Public License
Classifier: Topic :: Internet
Classifier: Topic :: Software Development :: Documentation
